.bumpversion.cfg
.gitignore
.gitlab-ci.yml
LICENSE
Makefile
PKGBUILD
README.md
VERSION
makefilet-download-ondemand.mk
setup.cfg
setup.py
tox.ini
debian/changelog
debian/compat
debian/control
debian/copyright
debian/rules
debian/source/format
docs/onkyio-pi.md
docs/images/rpi1_back.jpg
docs/images/rpi1_front.jpg
onkyrimote/__init__.py
onkyrimote/__main__.py
onkyrimote/protocol.py
onkyrimote.egg-info/PKG-INFO
onkyrimote.egg-info/SOURCES.txt
onkyrimote.egg-info/dependency_links.txt
onkyrimote.egg-info/entry_points.txt
onkyrimote.egg-info/requires.txt
onkyrimote.egg-info/top_level.txt
onkyrimote/backend/__init__.py
onkyrimote/backend/pigpio.py
onkyrimote/device/__init__.py
onkyrimote/device/onkyo.py