Metadata-Version: 2.1
Name: onkyrimote
Version: 0.2.0
Summary: Python library and command line utility for controlling Onkyo receivers through the RI protocol.
Home-page: https://github.com/kmohrf/onkyrimote
Author: Konrad Mohrfeldt
Author-email: konrad.mohrfeldt@farbdev.org
License: AGPLv3+
Platform: UNKNOWN
Classifier: License :: OSI Approved :: GNU Affero General Public License v3 or later (AGPLv3+)
Classifier: Programming Language :: Python
Classifier: Programming Language :: Python :: 3
Classifier: Development Status :: 4 - Beta
Provides-Extra: pi
